functools_extra/__init__.py
functools_extra/functiongroup.py
functools_extra/pipe.py
functools_extra/pipe_builder.py
functools_extra-0.3.0.dist-info/METADATA
functools_extra-0.3.0.dist-info/WHEEL
functools_extra-0.3.0.dist-info/entry_points.txt
functools_extra-0.3.0.dist-info/licenses/LICENSE
functools_extra-0.3.0.dist-info/RECORD
