Metadata-Version: 2.1
Name: functools-extra
Version: 0.3.0
Summary: Additional functional tools for python not covered in the functools library
Project-URL: Homepage, https://github.com/dennisrall/functools-extra
Project-URL: Documentation, https://github.com/dennisrall/functools-extra
Project-URL: Repository, https://github.com/dennisrall/functools-extra
Project-URL: Issues, https://github.com/dennisrall/functools-extra/issues
Project-URL: Changelog, https://github.com/dennisrall/functools-extra/releases
Author-email: Dennis Rall <dennis.rall@web.de>
License: MIT License
License-File: LICENSE
Keywords: functional,python,tools
Classifier: License :: OSI Approved :: MIT License
Classifier: Operating System :: OS Independent
Classifier: Programming Language :: Python :: 3
Requires-Python: >=3.8
